kedro_boot/__init__.py
kedro_boot/utils.py
kedro_boot/app/__init__.py
kedro_boot/app/app.py
kedro_boot/app/booter.py
kedro_boot/app/fastapi/__init__.py
kedro_boot/app/fastapi/app.py
kedro_boot/app/fastapi/cli.py
kedro_boot/app/fastapi/session.py
kedro_boot/app/fastapi/gunicorn/__init__.py
kedro_boot/app/fastapi/gunicorn/app.py
kedro_boot/app/fastapi/gunicorn/config.py
kedro_boot/app/fastapi/starter_apps/__init__.py
kedro_boot/app/fastapi/starter_apps/runner.py
kedro_boot/framework/__init__.py
kedro_boot/framework/adapter.py
kedro_boot/framework/hooks.py
kedro_boot/framework/cli/__init__.py
kedro_boot/framework/cli/cli.py
kedro_boot/framework/cli/factory.py
kedro_boot/framework/cli/utils.py
kedro_boot/framework/compiler/__init__.py
kedro_boot/framework/compiler/compiler.py
kedro_boot/framework/compiler/specs.py
kedro_boot/framework/context/__init__.py
kedro_boot/framework/context/context.py
kedro_boot/framework/renderer/__init__.py
kedro_boot/framework/renderer/renderer.py
kedro_boot/framework/session/__init__.py
kedro_boot/framework/session/runner.py
kedro_boot/framework/session/session.py
kedro_boot-0.3.0.dist-info/licenses/LICENSE
tests/app/__init__.py
tests/app/test_booter.py
tests/framework/__init__.py
tests/framework/test_session.py
kedro_boot-0.3.0.dist-info/METADATA
kedro_boot-0.3.0.dist-info/WHEEL
kedro_boot-0.3.0.dist-info/entry_points.txt
kedro_boot-0.3.0.dist-info/top_level.txt
kedro_boot-0.3.0.dist-info/RECORD
