Metadata-Version: 2.4
Name: kedro-boot
Version: 0.3.0
Summary: A kedro plugin that streamlines the integration between Kedro projects and external applications, making it easier for you to develop production-ready data science applications.
Home-page: https://github.com/takikadiri/kedro-boot
Author: Takieddine Kadiri
License: Apache Software License (Apache 2.0)
Keywords: kedro-plugin,framework,data apps,pipelines,machine learning,data pipelines,data science,data engineering,model serving,mlops,dataops
Classifier: Programming Language :: Python :: 3
Classifier: Framework :: Kedro
Classifier: Intended Audience :: Developers
Classifier: Operating System :: Microsoft :: Windows
Classifier: Operating System :: MacOS
Classifier: Operating System :: POSIX :: Linux
Requires-Python: >=3.8
License-File: LICENSE
Requires-Dist: kedro<2.0,>=1.0.0
Provides-Extra: doc
Requires-Dist: sphinx<8.0.0,>=4.5.0; extra == "doc"
Requires-Dist: sphinx_rtd_theme<1.4,>=1.0; extra == "doc"
Requires-Dist: sphinx-markdown-tables~=0.0.15; extra == "doc"
Requires-Dist: sphinx-click<5.1,>=3.1; extra == "doc"
Requires-Dist: sphinx_copybutton~=0.5.0; extra == "doc"
Requires-Dist: myst-parser<2.1.0,>=0.17.2; extra == "doc"
Provides-Extra: test
Requires-Dist: pytest<8.0.0,>=5.4.0; extra == "test"
Requires-Dist: pytest-cov<5.0.0,>=2.8.0; extra == "test"
Requires-Dist: pytest-lazy-fixture<1.0.0,>=0.6.0; extra == "test"
Requires-Dist: pytest-mock<4.0.0,>=3.1.0; extra == "test"
Requires-Dist: ruff; extra == "test"
Requires-Dist: scikit-learn~=1.0; extra == "test"
Requires-Dist: kedro-datasets[pandas.CSVDataset,pandas.ExcelDataset,pandas.ParquetDataset]>=8.0.0; extra == "test"
Provides-Extra: dev
Requires-Dist: pre-commit<4.0.0,>=2.0.0; extra == "dev"
Requires-Dist: jupyter<2.0.0,>=1.0.0; extra == "dev"
Provides-Extra: fastapi
Requires-Dist: fastapi>=0.100.0; extra == "fastapi"
Requires-Dist: gunicorn>=23.0.0; extra == "fastapi"
Requires-Dist: pyctuator>=1.2.0; extra == "fastapi"
Requires-Dist: uvicorn[standard]>=0.12.0; extra == "fastapi"
Dynamic: author
Dynamic: classifier
Dynamic: description
Dynamic: description-content-type
Dynamic: home-page
Dynamic: keywords
Dynamic: license
Dynamic: license-file
Dynamic: provides-extra
Dynamic: requires-dist
Dynamic: requires-python
Dynamic: summary
